{
    "EUN1_3719577676": {
        "top4": false,
        "top1": false,
        "units": "TFT13_Morgana, TFT13_Vladimir, TFT13_Blitzcrank, TFT13_Cassiopeia, TFT13_Elise, TFT13_Silco, TFT13_Silco, TFT13_DrMundo, TFT13_LeBlanc, TFT13_Sion"
    },
    "EUN1_3718979826": {
        "top4": false,
        "top1": false,
        "units": "TFT13_Leona, TFT13_Rell, TFT13_Ezreal, TFT13_Beardy, TFT13_Illaoi, TFT13_Jayce, TFT13_Viktor, TFT13_MissMage, TFT13_JayceSummon"
    },
    "EUN1_3720341858": {
        "top4": false,
        "top1": false,
        "units": "TFT13_Lux, TFT13_Singed, TFT13_Irelia, TFT13_Leona, TFT13_Rell, TFT13_Beardy, TFT13_Illaoi, TFT13_Jayce, TFT13_JayceSummon"
    },
    "EUN1_3714062697": {
        "top4": false,
        "top1": false,
        "units": "TFT13_Tristana, TFT13_Urgot, TFT13_Ezreal, TFT13_Nami, TFT13_Ambessa, TFT13_Garen, TFT13_Corki, TFT13_Rumble"
    },
    "EUN1_3720904714": {
        "top4": false,
        "top1": false,
        "units": "TFT13_Trundle, TFT13_Urgot, TFT13_Ziggs, TFT13_Gangplank, tft13_elise, TFT13_Ekko, TFT13_Illaoi, TFT13_Corki, TFT13_Rumble"
    },
    "EUN1_3720432753": {
        "top4": false,
        "top1": false,
        "units": "TFT13_Darius, TFT13_Draven, TFT13_Blue, TFT13_Red, TFT13_Urgot, TFT13_Prime, TFT13_Gangplank"
    }
}