{
    "EUN1_3716542553": {
        "top4": true,
        "top1": true,
        "units": "TFT13_Irelia, TFT13_Akali, TFT13_Sett, TFT13_Ezreal, TFT13_Ekko, TFT13_Illaoi, TFT13_Zoe, TFT13_LeBlanc, TFT13_Rumble, TFT13_Jinx"
    },
    "EUN1_3717545675": {
        "top4": true,
        "top1": true,
        "units": "TFT13_Lux, TFT13_Singed, TFT13_Irelia, TFT13_Leona, TFT13_Rell, TFT13_Illaoi, TFT13_Zoe, TFT13_Jayce, TFT13_LeBlanc, TFT13_Rumble, TFT13_JayceSummon"
    },
    "EUN1_3717530810": {
        "top4": true,
        "top1": true,
        "units": "TFT13_Irelia, TFT13_Sett, TFT13_Ezreal, TFT13_Nami, TFT13_Ekko, TFT13_Illaoi, TFT13_Zoe, TFT13_Rumble, tft13_jinx"
    },
    "EUN1_3714238607": {
        "top4": false,
        "top1": false,
        "units": "TFT13_Morgana, TFT13_Vladimir, TFT13_Cassiopeia, tft13_elise, TFT13_Silco, TFT13_Garen, TFT13_DrMundo, TFT13_LeBlanc, TFT13_Mordekaiser, TFT13_Sion"
    }
}