{
    "EUW1_7219405455": {
        "top4": false,
        "top1": false,
        "units": "TFT13_Blue, TFT13_Zeri, TFT13_Camille, TFT13_Gremlin, TFT13_Gremlin, TFT13_FlyGuy, TFT13_Garen, TFT13_Ekko"
    },
    "EUW1_7239781132": {
        "top4": false,
        "top1": false,
        "units": "TFT13_Vladimir, TFT13_Rell, TFT13_Ziggs, tft13_swain, TFT13_Blitzcrank, TFT13_Cassiopeia, tft13_elise, TFT13_Silco, TFT13_Sion"
    },
    "EUW1_7254536487": {
        "top4": true,
        "top1": true,
        "units": "TFT13_Morgana, TFT13_Vladimir, TFT13_Cassiopeia, tft13_elise, TFT13_Silco, TFT13_Garen, TFT13_LeBlanc, TFT13_Rumble, TFT13_Viktor, TFT13_Sion"
    },
    "EUW1_7205900901": {
        "top4": true,
        "top1": false,
        "units": "TFT13_Morgana, TFT13_Vladimir, TFT13_Cassiopeia, TFT13_Heimerdinger, tft13_elise, TFT13_Garen, TFT13_Jayce, TFT13_Malzahar, TFT13_LeBlanc, TFT13_Sion, TFT13_JayceSummon"
    },
    "EUW1_7204727226": {
        "top4": false,
        "top1": false,
        "units": "TFT13_Blue, TFT13_Trundle, TFT13_Ziggs, TFT13_Gangplank, TFT13_Ekko, TFT13_Corki, TFT13_Jayce, TFT13_Lieutenant, TFT13_Rumble, TFT13_JayceSummon"
    }
}