{
    "EUW1_7218998283": {
        "top4": false,
        "top1": false,
        "units": "TFT13_Blue, TFT13_Urgot, TFT13_Camille, TFT13_Gremlin, TFT13_FlyGuy, TFT13_Beardy, TFT13_Garen, TFT13_Ekko, TFT13_Illaoi"
    },
    "EUW1_7240516177": {
        "top4": false,
        "top1": false,
        "units": "TFT13_Amumu, TFT13_Nocturne, tft13_swain, TFT13_Blitzcrank, TFT13_KogMaw, TFT13_Garen, TFT13_Malzahar"
    },
    "EUW1_7240500389": {
        "top4": false,
        "top1": false,
        "units": "TFT13_Blue, TFT13_Trundle, tft13_swain, TFT13_Gangplank, tft13_elise, TFT13_Ekko, TFT13_Corki, TFT13_Jayce, TFT13_JayceSummon"
    },
    "EUW1_7240484944": {
        "top4": true,
        "top1": false,
        "units": "TFT13_Irelia, TFT13_Leona, TFT13_Tristana, TFT13_Ezreal, TFT13_Beardy, TFT13_Illaoi, TFT13_Corki, TFT13_Jayce, TFT13_JayceSummon"
    }
}